.bytecode 50.0
.class public synchronized com/elevenpaths/android/latch/activities/A_Landing
.super android/app/Activity

.field private 'a' Landroid/support/v4/view/ViewPager;

.method public <init>()V
aload 0
invokespecial android/app/Activity/<init>()V
return
.limit locals 1
.limit stack 1
.end method

.method private b()V
aload 0
ldc_w 2131099701
invokevirtual com/elevenpaths/android/latch/activities/A_Landing/findViewById(I)Landroid/view/View;
checkcast android/widget/TextView
astore 1
aload 0
ldc_w 2131099705
invokevirtual com/elevenpaths/android/latch/activities/A_Landing/findViewById(I)Landroid/view/View;
checkcast android/widget/TextView
astore 2
aload 0
ldc_w 2131099708
invokevirtual com/elevenpaths/android/latch/activities/A_Landing/findViewById(I)Landroid/view/View;
checkcast android/widget/TextView
astore 3
aload 0
ldc_w 2131099711
invokevirtual com/elevenpaths/android/latch/activities/A_Landing/findViewById(I)Landroid/view/View;
checkcast android/widget/TextView
astore 4
aload 0
ldc_w 2131099714
invokevirtual com/elevenpaths/android/latch/activities/A_Landing/findViewById(I)Landroid/view/View;
checkcast android/widget/TextView
astore 5
aload 0
ldc_w 2131099717
invokevirtual com/elevenpaths/android/latch/activities/A_Landing/findViewById(I)Landroid/view/View;
checkcast android/widget/TextView
astore 6
aload 0
ldc_w 2131099702
invokevirtual com/elevenpaths/android/latch/activities/A_Landing/findViewById(I)Landroid/view/View;
checkcast android/widget/TextView
astore 7
aload 0
ldc_w 2131099706
invokevirtual com/elevenpaths/android/latch/activities/A_Landing/findViewById(I)Landroid/view/View;
checkcast android/widget/TextView
astore 8
aload 0
ldc_w 2131099709
invokevirtual com/elevenpaths/android/latch/activities/A_Landing/findViewById(I)Landroid/view/View;
checkcast android/widget/TextView
astore 9
aload 0
ldc_w 2131099712
invokevirtual com/elevenpaths/android/latch/activities/A_Landing/findViewById(I)Landroid/view/View;
checkcast android/widget/TextView
astore 10
aload 0
ldc_w 2131099715
invokevirtual com/elevenpaths/android/latch/activities/A_Landing/findViewById(I)Landroid/view/View;
checkcast android/widget/TextView
astore 11
aload 0
ldc_w 2131099718
invokevirtual com/elevenpaths/android/latch/activities/A_Landing/findViewById(I)Landroid/view/View;
checkcast android/widget/TextView
astore 12
aload 0
ldc_w 2131099721
invokevirtual com/elevenpaths/android/latch/activities/A_Landing/findViewById(I)Landroid/view/View;
checkcast android/widget/TextView
astore 13
aload 1
ldc "fonts/roboto_light.ttf"
invokestatic com/elevenpaths/android/latch/h/d/a(Landroid/widget/TextView;Ljava/lang/String;)V
aload 2
ldc "fonts/roboto_light.ttf"
invokestatic com/elevenpaths/android/latch/h/d/a(Landroid/widget/TextView;Ljava/lang/String;)V
aload 3
ldc "fonts/roboto_light.ttf"
invokestatic com/elevenpaths/android/latch/h/d/a(Landroid/widget/TextView;Ljava/lang/String;)V
aload 4
ldc "fonts/roboto_light.ttf"
invokestatic com/elevenpaths/android/latch/h/d/a(Landroid/widget/TextView;Ljava/lang/String;)V
aload 5
ldc "fonts/roboto_light.ttf"
invokestatic com/elevenpaths/android/latch/h/d/a(Landroid/widget/TextView;Ljava/lang/String;)V
aload 6
ldc "fonts/roboto_light.ttf"
invokestatic com/elevenpaths/android/latch/h/d/a(Landroid/widget/TextView;Ljava/lang/String;)V
aload 7
ldc "fonts/roboto_light.ttf"
invokestatic com/elevenpaths/android/latch/h/d/a(Landroid/widget/TextView;Ljava/lang/String;)V
aload 8
ldc "fonts/roboto_light.ttf"
invokestatic com/elevenpaths/android/latch/h/d/a(Landroid/widget/TextView;Ljava/lang/String;)V
aload 9
ldc "fonts/roboto_light.ttf"
invokestatic com/elevenpaths/android/latch/h/d/a(Landroid/widget/TextView;Ljava/lang/String;)V
aload 10
ldc "fonts/roboto_light.ttf"
invokestatic com/elevenpaths/android/latch/h/d/a(Landroid/widget/TextView;Ljava/lang/String;)V
aload 11
ldc "fonts/roboto_light.ttf"
invokestatic com/elevenpaths/android/latch/h/d/a(Landroid/widget/TextView;Ljava/lang/String;)V
aload 12
ldc "fonts/roboto_light.ttf"
invokestatic com/elevenpaths/android/latch/h/d/a(Landroid/widget/TextView;Ljava/lang/String;)V
aload 13
ldc "fonts/roboto_light.ttf"
invokestatic com/elevenpaths/android/latch/h/d/a(Landroid/widget/TextView;Ljava/lang/String;)V
return
.limit locals 14
.limit stack 2
.end method

.method public a()V
aload 0
ldc_w 2131099703
invokevirtual com/elevenpaths/android/latch/activities/A_Landing/findViewById(I)Landroid/view/View;
checkcast android/widget/Button
astore 1
aload 1
ldc "fonts/roboto_light.ttf"
invokestatic com/elevenpaths/android/latch/h/d/a(Landroid/widget/Button;Ljava/lang/String;)V
aload 1
new com/elevenpaths/android/latch/activities/b
dup
aload 0
invokespecial com/elevenpaths/android/latch/activities/b/<init>(Lcom/elevenpaths/android/latch/activities/A_Landing;)V
invokevirtual android/widget/Button/setOnClickListener(Landroid/view/View$OnClickListener;)V
aload 0
ldc_w 2131099720
invokevirtual com/elevenpaths/android/latch/activities/A_Landing/findViewById(I)Landroid/view/View;
checkcast android/widget/Button
astore 2
aload 2
ldc "fonts/roboto_light.ttf"
invokestatic com/elevenpaths/android/latch/h/d/a(Landroid/widget/Button;Ljava/lang/String;)V
aload 2
new com/elevenpaths/android/latch/activities/c
dup
aload 0
invokespecial com/elevenpaths/android/latch/activities/c/<init>(Lcom/elevenpaths/android/latch/activities/A_Landing;)V
invokevirtual android/widget/Button/setOnClickListener(Landroid/view/View$OnClickListener;)V
aload 0
ldc_w 2131099722
invokevirtual com/elevenpaths/android/latch/activities/A_Landing/findViewById(I)Landroid/view/View;
checkcast android/widget/TextView
astore 3
aload 3
ldc "fonts/roboto_light.ttf"
invokestatic com/elevenpaths/android/latch/h/d/a(Landroid/widget/TextView;Ljava/lang/String;)V
aload 3
new com/elevenpaths/android/latch/activities/d
dup
aload 0
invokespecial com/elevenpaths/android/latch/activities/d/<init>(Lcom/elevenpaths/android/latch/activities/A_Landing;)V
invokevirtual android/widget/TextView/setOnClickListener(Landroid/view/View$OnClickListener;)V
aload 0
ldc_w 2131099719
invokevirtual com/elevenpaths/android/latch/activities/A_Landing/findViewById(I)Landroid/view/View;
checkcast android/widget/Button
astore 4
aload 4
ldc "fonts/roboto_light.ttf"
invokestatic com/elevenpaths/android/latch/h/d/a(Landroid/widget/Button;Ljava/lang/String;)V
aload 4
new com/elevenpaths/android/latch/activities/e
dup
aload 0
invokespecial com/elevenpaths/android/latch/activities/e/<init>(Lcom/elevenpaths/android/latch/activities/A_Landing;)V
invokevirtual android/widget/Button/setOnClickListener(Landroid/view/View$OnClickListener;)V
return
.limit locals 5
.limit stack 4
.end method

.method public a(I)V
aload 0
ldc_w 2131099691
invokevirtual com/elevenpaths/android/latch/activities/A_Landing/findViewById(I)Landroid/view/View;
checkcast android/widget/ImageView
astore 2
aload 0
ldc_w 2131099692
invokevirtual com/elevenpaths/android/latch/activities/A_Landing/findViewById(I)Landroid/view/View;
checkcast android/widget/ImageView
astore 3
aload 0
ldc_w 2131099693
invokevirtual com/elevenpaths/android/latch/activities/A_Landing/findViewById(I)Landroid/view/View;
checkcast android/widget/ImageView
astore 4
aload 0
ldc_w 2131099694
invokevirtual com/elevenpaths/android/latch/activities/A_Landing/findViewById(I)Landroid/view/View;
checkcast android/widget/ImageView
astore 5
aload 0
ldc_w 2131099695
invokevirtual com/elevenpaths/android/latch/activities/A_Landing/findViewById(I)Landroid/view/View;
checkcast android/widget/ImageView
astore 6
aload 0
ldc_w 2131099696
invokevirtual com/elevenpaths/android/latch/activities/A_Landing/findViewById(I)Landroid/view/View;
checkcast android/widget/ImageView
astore 7
aload 2
ldc_w 2130837776
invokevirtual android/widget/ImageView/setImageResource(I)V
aload 3
ldc_w 2130837776
invokevirtual android/widget/ImageView/setImageResource(I)V
aload 4
ldc_w 2130837776
invokevirtual android/widget/ImageView/setImageResource(I)V
aload 5
ldc_w 2130837776
invokevirtual android/widget/ImageView/setImageResource(I)V
aload 6
ldc_w 2130837776
invokevirtual android/widget/ImageView/setImageResource(I)V
aload 7
ldc_w 2130837776
invokevirtual android/widget/ImageView/setImageResource(I)V
iload 1
tableswitch 0
L0
L1
L2
L3
L4
L5
default : L6
L6:
return
L0:
aload 2
ldc_w 2130837775
invokevirtual android/widget/ImageView/setImageResource(I)V
return
L1:
aload 3
ldc_w 2130837775
invokevirtual android/widget/ImageView/setImageResource(I)V
return
L2:
aload 4
ldc_w 2130837775
invokevirtual android/widget/ImageView/setImageResource(I)V
return
L3:
aload 5
ldc_w 2130837775
invokevirtual android/widget/ImageView/setImageResource(I)V
return
L4:
aload 6
ldc_w 2130837775
invokevirtual android/widget/ImageView/setImageResource(I)V
return
L5:
aload 7
ldc_w 2130837775
invokevirtual android/widget/ImageView/setImageResource(I)V
return
.limit locals 8
.limit stack 2
.end method

.method protected onCreate(Landroid/os/Bundle;)V
.catch android/content/pm/PackageManager$NameNotFoundException from L0 to L1 using L2
aload 0
aload 1
invokespecial android/app/Activity/onCreate(Landroid/os/Bundle;)V
new com/elevenpaths/android/latch/g/b
dup
aload 0
invokespecial com/elevenpaths/android/latch/g/b/<init>(Landroid/app/Activity;)V
astore 2
aload 2
invokevirtual com/elevenpaths/android/latch/g/b/a()Z
ifeq L3
aload 2
invokevirtual com/elevenpaths/android/latch/g/b/c()V
return
L3:
aload 0
ldc_w 2130903040
invokevirtual com/elevenpaths/android/latch/activities/A_Landing/setContentView(I)V

; Toast.makeText(this.getApplicationContext(), "Latch Modificat", Toast.LENGTH_LONG).show();
aload 0
invokevirtual com/elevenpaths/android/latch/activities/A_Landing/getApplicationContext()Landroid/content/Context;
ldc "AutoLatch plugin on"
ldc_w 1
invokestatic android/widget/Toast/makeText(Landroid/content/Context;Ljava/lang/CharSequence;I)Landroid/widget/Toast;
invokevirtual android/widget/Toast/show()V

aload 0
aload 0
ldc_w 2131099697
invokevirtual com/elevenpaths/android/latch/activities/A_Landing/findViewById(I)Landroid/view/View;
checkcast android/support/v4/view/ViewPager
putfield com/elevenpaths/android/latch/activities/A_Landing/a Landroid/support/v4/view/ViewPager;
new com/elevenpaths/android/latch/activities/f
dup
aload 0
invokespecial com/elevenpaths/android/latch/activities/f/<init>(Lcom/elevenpaths/android/latch/activities/A_Landing;)V
astore 3
aload 0
getfield com/elevenpaths/android/latch/activities/A_Landing/a Landroid/support/v4/view/ViewPager;
aload 3
invokevirtual android/support/v4/view/ViewPager/setAdapter(Landroid/support/v4/view/ao;)V
aload 0
getfield com/elevenpaths/android/latch/activities/A_Landing/a Landroid/support/v4/view/ViewPager;
new com/elevenpaths/android/latch/activities/a
dup
aload 0
invokespecial com/elevenpaths/android/latch/activities/a/<init>(Lcom/elevenpaths/android/latch/activities/A_Landing;)V
invokevirtual android/support/v4/view/ViewPager/setOnPageChangeListener(Landroid/support/v4/view/bx;)V
ldc ""
astore 4
L0:
invokestatic com/elevenpaths/android/latch/LatchApplication/d()Lcom/elevenpaths/android/latch/LatchApplication;
invokevirtual com/elevenpaths/android/latch/LatchApplication/getPackageManager()Landroid/content/pm/PackageManager;
aload 0
invokevirtual com/elevenpaths/android/latch/activities/A_Landing/getPackageName()Ljava/lang/String;
iconst_0
invokevirtual android/content/pm/PackageManager/getPackageInfo(Ljava/lang/String;I)Landroid/content/pm/PackageInfo;
getfield android/content/pm/PackageInfo/versionName Ljava/lang/String;
astore 4
new java/lang/StringBuilder
dup
invokespecial java/lang/StringBuilder/<init>()V
aload 4
invokevirtual java/lang/StringBuilder/append(Ljava/lang/String;)Ljava/lang/StringBuilder;
ldc ""
invokevirtual java/lang/StringBuilder/append(Ljava/lang/String;)Ljava/lang/StringBuilder;
invokevirtual java/lang/StringBuilder/toString()Ljava/lang/String;
astore 8
L1:
aload 8
astore 6
L4:
aload 0
ldc_w 2131099699
invokevirtual com/elevenpaths/android/latch/activities/A_Landing/findViewById(I)Landroid/view/View;
checkcast android/widget/TextView
astore 7
aload 7
new java/lang/StringBuilder
dup
invokespecial java/lang/StringBuilder/<init>()V
aload 0
ldc_w 2131361865
invokevirtual com/elevenpaths/android/latch/activities/A_Landing/getString(I)Ljava/lang/String;
invokevirtual java/lang/StringBuilder/append(Ljava/lang/String;)Ljava/lang/StringBuilder;
ldc " "
invokevirtual java/lang/StringBuilder/append(Ljava/lang/String;)Ljava/lang/StringBuilder;
aload 6
invokevirtual java/lang/StringBuilder/append(Ljava/lang/String;)Ljava/lang/StringBuilder;
invokevirtual java/lang/StringBuilder/toString()Ljava/lang/String;
invokevirtual android/widget/TextView/setText(Ljava/lang/CharSequence;)V
aload 7
ldc "fonts/roboto_light.ttf"
invokestatic com/elevenpaths/android/latch/h/d/a(Landroid/widget/TextView;Ljava/lang/String;)V
aload 0
iconst_0
invokevirtual com/elevenpaths/android/latch/activities/A_Landing/a(I)V
aload 0
invokevirtual com/elevenpaths/android/latch/activities/A_Landing/a()V
aload 0
invokespecial com/elevenpaths/android/latch/activities/A_Landing/b()V
aload 0
invokestatic com/elevenpaths/android/latch/b/b(Landroid/app/Activity;)V
return
L2:
astore 5
aload 4
astore 6
goto L4
.limit locals 9
.limit stack 4
.end method

.method protected onPause()V
aload 0
invokespecial android/app/Activity/onPause()V
invokestatic com/elevenpaths/android/latch/LatchApplication/g()V
return
.limit locals 1
.limit stack 1
.end method

.method protected onResume()V
aload 0
invokespecial android/app/Activity/onResume()V
invokestatic com/elevenpaths/android/latch/LatchApplication/f()V
return
.limit locals 1
.limit stack 1
.end method
